README.rst
setup.py
src/pytest_django_lite/__init__.py
src/pytest_django_lite/plugin.py
src/pytest_django_lite.egg-info/PKG-INFO
src/pytest_django_lite.egg-info/SOURCES.txt
src/pytest_django_lite.egg-info/dependency_links.txt
src/pytest_django_lite.egg-info/entry_points.txt
src/pytest_django_lite.egg-info/requires.txt
src/pytest_django_lite.egg-info/top_level.txt