Metadata-Version: 1.0
Name: pytest-django-lite
Version: 0.1.1
Summary: The bare minimum to integrate py.test with Django.
Home-page: https://github.com/dcramer/pytest-django-lite
Author: David Cramer
Author-email: dcramer@gmail.com
License: Apache License 2.0
Platform: UNKNOWN
